dyncusum/__init__.py
dyncusum/core.py
dyncusum/critical_values.py
dyncusum/power_analysis.py
dyncusum/tables.py
dyncusum/utils.py
dyncusum/visualization.py
dyncusum-1.0.0.dist-info/METADATA
dyncusum-1.0.0.dist-info/WHEEL
dyncusum-1.0.0.dist-info/top_level.txt
dyncusum-1.0.0.dist-info/RECORD
